dietnb/__init__.py
dietnb/_cli.py
dietnb/_core.py
dietnb/_startup.py
dietnb-0.2.1.dist-info/licenses/LICENSE
tests/test_activation.py
dietnb-0.2.1.dist-info/METADATA
dietnb-0.2.1.dist-info/WHEEL
dietnb-0.2.1.dist-info/entry_points.txt
dietnb-0.2.1.dist-info/top_level.txt
dietnb-0.2.1.dist-info/RECORD
